gpt2md/__init__.py
gpt2md/cli.py
gpt2md/main.py
gpt2md-0.1.dist-info/LICENSE
gpt2md-0.1.dist-info/METADATA
gpt2md-0.1.dist-info/WHEEL
gpt2md-0.1.dist-info/entry_points.txt
gpt2md-0.1.dist-info/top_level.txt
gpt2md-0.1.dist-info/RECORD
