Metadata-Version: 2.1
Name: gpt2md
Version: 0.1
Summary: A simple tool to convert your ChatGPT conversation to Markdown files.
Author-email: Yoran Gyselen <yoran@gyselen.be>
License: MIT License
Project-URL: Homepage, https://github.com/Yoran-Gyselen/gpt2md
Project-URL: Bug Tracker, https://github.com/Yoran-Gyselen/gpt2md/issues
Requires-Python: >=3.9
License-File: LICENSE
